<?xml version="1.0" encoding="utf-8"?>
<annotation>
	<folder>images</folder>
	<filename>IPC_2021-05-13.10.12.10.5450.jpg</filename>
	<size>
		<width>2560</width>
		<height>960</height>
		<depth>3</depth>
	</size>
	<segmented>0</segmented>
	<object>
		<name>flower</name>
		<pose>Unspecified</pose>
		<truncated>0</truncated>
		<difficult>0</difficult>
		<bndbox>
			<xmin>1746</xmin>
			<ymin>269</ymin>
			<xmax>1951</xmax>
			<ymax>479</ymax>
		</bndbox>
	</object>
	<object>
		<name>flower</name>
		<pose>Unspecified</pose>
		<truncated>0</truncated>
		<difficult>0</difficult>
		<bndbox>
			<xmin>650</xmin>
			<ymin>258</ymin>
			<xmax>836</xmax>
			<ymax>434</ymax>
		</bndbox>
	</object>
</annotation>
