<?xml version="1.0" encoding="utf-8"?>
<annotation>
	<folder>images</folder>
	<filename>IPC_2021-05-13.17.02.06.9240.jpg</filename>
	<size>
		<width>2560</width>
		<height>960</height>
		<depth>3</depth>
	</size>
	<segmented>0</segmented>
	<object>
		<name>flower</name>
		<pose>Unspecified</pose>
		<truncated>0</truncated>
		<difficult>0</difficult>
		<bndbox>
			<xmin>391</xmin>
			<ymin>393</ymin>
			<xmax>601</xmax>
			<ymax>618</ymax>
		</bndbox>
	</object>
	<object>
		<name>flower</name>
		<pose>Unspecified</pose>
		<truncated>0</truncated>
		<difficult>0</difficult>
		<bndbox>
			<xmin>535</xmin>
			<ymin>284</ymin>
			<xmax>771</xmax>
			<ymax>552</ymax>
		</bndbox>
	</object>
	<object>
		<name>flower</name>
		<pose>Unspecified</pose>
		<truncated>0</truncated>
		<difficult>0</difficult>
		<bndbox>
			<xmin>1592</xmin>
			<ymin>320</ymin>
			<xmax>1831</xmax>
			<ymax>581</ymax>
		</bndbox>
	</object>
	<object>
		<name>flower</name>
		<pose>Unspecified</pose>
		<truncated>0</truncated>
		<difficult>0</difficult>
		<bndbox>
			<xmin>733</xmin>
			<ymin>408</ymin>
			<xmax>930</xmax>
			<ymax>573</ymax>
		</bndbox>
	</object>
	<object>
		<name>flower</name>
		<pose>Unspecified</pose>
		<truncated>0</truncated>
		<difficult>0</difficult>
		<bndbox>
			<xmin>1492</xmin>
			<ymin>459</ymin>
			<xmax>1683</xmax>
			<ymax>629</ymax>
		</bndbox>
	</object>
	<object>
		<name>flower</name>
		<pose>Unspecified</pose>
		<truncated>0</truncated>
		<difficult>0</difficult>
		<bndbox>
			<xmin>1789</xmin>
			<ymin>443</ymin>
			<xmax>1962</xmax>
			<ymax>601</ymax>
		</bndbox>
	</object>
</annotation>
